<?xml version="1.0" encoding="utf-8"?>
<!DOCTYPE hibernate-mapping PUBLIC "-//Hibernate/Hibernate Mapping DTD 3.0//EN"
"http://www.hibernate.org/dtd/hibernate-mapping-3.0.dtd">
<!-- 
    Mapping file autogenerated by MyEclipse Persistence Tools
-->
<hibernate-mapping>
    <class name="com.model.Inventory" table="inventory" catalog="sakila">
        <id name="inventoryId" type="java.lang.Integer">
            <column name="inventory_id" />
            <generator class="native" />
        </id>
        <many-to-one name="store" class="com.model.Store" fetch="select">
            <column name="store_id" not-null="true" />
        </many-to-one>
        <many-to-one name="film" class="com.model.Film" fetch="select">
            <column name="film_id" not-null="true" />
        </many-to-one>
        <property name="lastUpdate" type="java.sql.Timestamp">
            <column name="last_update" length="19" not-null="true" />
        </property>
        <set name="rentals" inverse="true">
            <key>
                <column name="inventory_id" not-null="true" />
            </key>
            <one-to-many class="com.model.Rental" />
        </set>
    </class>
</hibernate-mapping>
